[{"function": "standalone.loads.start", "arguments": {"keep_open": true}}, {"function": "standalone.loads.getLoads", "arguments": {"project_details": {"name": "Test", "id": "ID", "company": "BR", "designer": "Alex", "client": "Alex", "notes": "", "units": "metric", "logo": "https://platform.skyciv.com/storage/user_data/company_logos/noimage.png"}, "site_data": {"design_code": "nbcc2015", "project_address": "Sherbrooke, Qc, Canada", "topography": {"wind_direction": "N", "topo_image": true, "country": "Canada", "snow_area_classification": "other-cases", "terrain_category": "B"}, "ari": "50_years", "recurrence_interval": "50_years", "importance_level": "Normal", "limit_state": "ULS"}, "building_data": {"design_code": "nbcc2015", "structure": "building", "wind_parameters": {"structure_level": [{"floor_level": "2", "floor_elevation": "15"}, {"floor_level": "3", "floor_elevation": "20"}], "wall_cladding_area": 0, "roof_cladding_area": 0, "enclosure": "partially-enclosed", "cladding_pressure_type": "", "structure_type": "mwfrs"}, "snow_parameters": {"sloped_roof_surface_condition": "unobstructed-slippery", "balance_unbalance": false}, "roof_profile": "monoslope", "building_dimensions": {"length": 50, "width": "40", "roof_angle": 18.43, "reference_height": "20"}}, "site_analysis": {"terrain_category_all_direction": {"NE": null, "E": null, "SE": null, "S": null, "SW": null, "W": null, "NW": null}, "topo_factor_all_direction": {}, "lee_multiplier_all_direction": null, "hillshape_multiplier_all_direction": {}, "topography_all_directions": {}}, "api_version": 2}}]